poetry_test_project/__init__
poetry_test_project/test.py
poetry_test_project-0.1.0.dist-info/METADATA
poetry_test_project-0.1.0.dist-info/WHEEL
poetry_test_project-0.1.0.dist-info/RECORD
