Metadata-Version: 2.4
Name: poetry-test-project
Version: 0.1.0
Summary: 
Author: Example User
Author-email: example@example.com
Requires-Python: >=3.13
Classifier: Programming Language :: Python :: 3
Classifier: Programming Language :: Python :: 3.13
Classifier: Programming Language :: Python :: 3.14
Requires-Dist: requests (>=2.32.5,<3.0.0)
